{
  "generated_at": "2026-03-05T18:01:13.847519",
  "version": "v3.1",
  "source_video": "【道听途说169上】病患脑部开刀血液竟然溅入医学生眼睛！从那之后看见的世界截然不同，眼见一老太太要求她脱自己袜子，而她看见的那不是袜子，而是——",
  "source_bvid": "BV119feBnEF9",
  "ai_summaries": [],
  "current_stories": [
    {
      "name": "当期故事_17:35",
      "mention_count": 25,
      "bv_list": [],
      "time_markers": [
        "17:35"
      ],
      "comments": [
        {
          "content": "17:35 这里就看得出佛像还是太年轻，和表哥那只老资历鬼还是有差距。换表哥那只鬼的话这里的打法就是弄个天亮的幻像引诱投稿人睁开眼",
          "like_count": 10,
          "reply_count": 1,
          "author": "魔法少女小符"
        },
        {
          "content": "17:35 这里就看得出佛像还是太年轻，和表哥那只老资历鬼还是有差距。换表哥那只鬼的话这里的打法就是弄个天亮的幻像引诱投稿人睁开眼",
          "like_count": 10,
          "reply_count": 1,
          "author": "魔法少女小符"
        },
        {
          "content": "17:35 这里就看得出佛像还是太年轻，和表哥那只老资历鬼还是有差距。换表哥那只鬼的话这里的打法就是弄个天亮的幻像引诱投稿人睁开眼",
          "like_count": 10,
          "reply_count": 1,
          "author": "魔法少女小符"
        },
        {
          "content": "17:35 这里就看得出佛像还是太年轻，和表哥那只老资历鬼还是有差距。换表哥那只鬼的话这里的打法就是弄个天亮的幻像引诱投稿人睁开眼",
          "like_count": 10,
          "reply_count": 1,
          "author": "魔法少女小符"
        },
        {
          "content": "17:35 这里就看得出佛像还是太年轻，和表哥那只老资历鬼还是有差距。换表哥那只鬼的话这里的打法就是弄个天亮的幻像引诱投稿人睁开眼",
          "like_count": 10,
          "reply_count": 1,
          "author": "魔法少女小符"
        },
        {
          "content": "17:35 这里就看得出佛像还是太年轻，和表哥那只老资历鬼还是有差距。换表哥那只鬼的话这里的打法就是弄个天亮的幻像引诱投稿人睁开眼",
          "like_count": 10,
          "reply_count": 1,
          "author": "魔法少女小符"
        },
        {
          "content": "17:35 这里就看得出佛像还是太年轻，和表哥那只老资历鬼还是有差距。换表哥那只鬼的话这里的打法就是弄个天亮的幻像引诱投稿人睁开眼",
          "like_count": 10,
          "reply_count": 1,
          "author": "魔法少女小符"
        },
        {
          "content": "17:35 这里就看得出佛像还是太年轻，和表哥那只老资历鬼还是有差距。换表哥那只鬼的话这里的打法就是弄个天亮的幻像引诱投稿人睁开眼",
          "like_count": 10,
          "reply_count": 1,
          "author": "魔法少女小符"
        },
        {
          "content": "17:35 这里就看得出佛像还是太年轻，和表哥那只老资历鬼还是有差距。换表哥那只鬼的话这里的打法就是弄个天亮的幻像引诱投稿人睁开眼",
          "like_count": 10,
          "reply_count": 1,
          "author": "魔法少女小符"
        },
        {
          "content": "17:35 这里就看得出佛像还是太年轻，和表哥那只老资历鬼还是有差距。换表哥那只鬼的话这里的打法就是弄个天亮的幻像引诱投稿人睁开眼",
          "like_count": 10,
          "reply_count": 1,
          "author": "魔法少女小符"
        }
      ],
      "help_request_count": 0,
      "standard_format_count": 0,
      "time_with_story_count": 0,
      "category": "当期",
      "source_video": "【道听途说169上】病患脑部开刀血液竟然溅入医学生眼睛！从那之后看见的世界截然不同，眼见一老太太要求她脱自己袜子，而她看见的那不是袜子，而是——",
      "source_bvid": "BV119feBnEF9",
      "heat_score": 2557.0
    }
  ],
  "past_stories": [],
  "help_requests": [],
  "priority_bv_list": [],
  "total_comments": 450,
  "total_stories": 1
}